endersutils/__init__.py
endersutils/el_classes/component.py
endersutils/el_classes/game.py
endersutils/el_classes/gameobjects.py
endersutils/el_classes/physics.py
endersutils/el_classes/player.py
endersutils/el_funcs/getallindir.py
endersutils/el_funcs/getobjectsbyclass.py
endersutils/el_globs/globs.py
endersutils-0.5.4.dist-info/METADATA
endersutils-0.5.4.dist-info/WHEEL
endersutils-0.5.4.dist-info/top_level.txt
endersutils-0.5.4.dist-info/RECORD
