Metadata-Version: 2.1
Name: endersutils
Version: 0.5.4
Summary: Some utility commands that aren't really too useful but I use them a lot.
Author-email: EnderGames <business.endergames@gmail.com>
Classifier: Programming Language :: Python :: 3
Classifier: License :: OSI Approved :: MIT License
Classifier: Operating System :: OS Independent
Requires-Python: <3.12.0,>=3.0.0
